{
  "@microsoft/generator-sharepoint": {
    "whichFolder": "subdir",
    "solutionName": "eventonly",
    "environment": "spo",
    "packageManager": "npm",
    "componentType": "webpart",
    "template": "react",
    "componentName": "UpcomingEventsWebPart",
    "componentDescription": "Upcoming events with calendar",
    "plusBeta": false,
    "isCreatingSolution": true,
    "nodeVersion": "18.20.5",
    "sdksVersions": {
      "@microsoft/microsoft-graph-client": "3.0.2",
      "@microsoft/teams-js": "2.24.0"
    },
    "version": "1.20.0",
    "libraryName": "eventonly",
    "libraryId": "1c1c8d85-57a2-4d73-8878-a5a6d05f7d37",
    "solutionShortDescription": "eventonly description",
    "skipFeatureDeployment": true,
    "isDomainIsolated": false
  }
}
